analistaDeImagem/__init__.py
analistaDeImagem/core.py
AnalistaDeImagem-0.1.2.dist-info/LICENSE
AnalistaDeImagem-0.1.2.dist-info/METADATA
AnalistaDeImagem-0.1.2.dist-info/WHEEL
AnalistaDeImagem-0.1.2.dist-info/top_level.txt
AnalistaDeImagem-0.1.2.dist-info/RECORD
